bizzmq/__init__.py
bizzmq/client.py
bizzmq/consumer.py
bizzmq/message.py
bizzmq/producer.py
bizzmq/queue.py
bizzmq/redis_client.py
bizzmq-0.1.0.dist-info/METADATA
bizzmq-0.1.0.dist-info/WHEEL
bizzmq-0.1.0.dist-info/top_level.txt
bizzmq-0.1.0.dist-info/RECORD
